deltaglider/__init__.py
deltaglider/_version.py
deltaglider/client.py
deltaglider/client_delete_helpers.py
deltaglider/client_models.py
deltaglider/py.typed
deltaglider/response_builders.py
deltaglider/types.py
deltaglider/adapters/__init__.py
deltaglider/adapters/cache_cas.py
deltaglider/adapters/cache_encrypted.py
deltaglider/adapters/cache_fs.py
deltaglider/adapters/cache_memory.py
deltaglider/adapters/clock_utc.py
deltaglider/adapters/diff_xdelta.py
deltaglider/adapters/ec2_metadata.py
deltaglider/adapters/hash_sha.py
deltaglider/adapters/logger_std.py
deltaglider/adapters/metrics_cloudwatch.py
deltaglider/adapters/metrics_noop.py
deltaglider/adapters/storage_s3.py
deltaglider/app/__init__.py
deltaglider/app/cli/__init__.py
deltaglider/app/cli/aws_compat.py
deltaglider/app/cli/main.py
deltaglider/app/cli/sync.py
deltaglider/client_operations/__init__.py
deltaglider/client_operations/batch.py
deltaglider/client_operations/bucket.py
deltaglider/client_operations/presigned.py
deltaglider/client_operations/stats.py
deltaglider/core/__init__.py
deltaglider/core/delta_extensions.py
deltaglider/core/errors.py
deltaglider/core/models.py
deltaglider/core/object_listing.py
deltaglider/core/s3_uri.py
deltaglider/core/service.py
deltaglider/ports/__init__.py
deltaglider/ports/cache.py
deltaglider/ports/clock.py
deltaglider/ports/diff.py
deltaglider/ports/hash.py
deltaglider/ports/logger.py
deltaglider/ports/metrics.py
deltaglider/ports/storage.py
deltaglider-6.0.2.dist-info/licenses/LICENSE
deltaglider-6.0.2.dist-info/METADATA
deltaglider-6.0.2.dist-info/WHEEL
deltaglider-6.0.2.dist-info/entry_points.txt
deltaglider-6.0.2.dist-info/top_level.txt
deltaglider-6.0.2.dist-info/RECORD
