Metadata-Version: 2.4
Name: deltaglider
Version: 6.0.2
Summary: Store 4TB in 5GB: S3-compatible storage with 99.9% compression for versioned files
Author-email: Beshu Tech <info@beshu.tech>
Maintainer-email: Beshu Tech Team <info@beshu.tech>
License-Expression: MIT
Project-URL: Homepage, https://github.com/beshu-tech/deltaglider
Project-URL: Documentation, https://github.com/beshu-tech/deltaglider#readme
Project-URL: Repository, https://github.com/beshu-tech/deltaglider
Project-URL: Issues, https://github.com/beshu-tech/deltaglider/issues
Project-URL: Changelog, https://github.com/beshu-tech/deltaglider/releases
Project-URL: Case Study, https://github.com/beshu-tech/deltaglider/blob/main/docs/case-study-readonlyrest.md
Keywords: s3,compression,delta,storage,backup,deduplication,xdelta3,binary-diff,artifact-storage,version-control,minio,aws,cost-optimization,devops
Classifier: Development Status :: 4 - Beta
Classifier: Intended Audience :: Developers
Classifier: Intended Audience :: System Administrators
Classifier: Operating System :: OS Independent
Classifier: Programming Language :: Python :: 3
Classifier: Programming Language :: Python :: 3.11
Classifier: Programming Language :: Python :: 3.12
Classifier: Programming Language :: Python :: 3.13
Classifier: Topic :: Software Development :: Libraries :: Python Modules
Classifier: Topic :: System :: Archiving :: Backup
Classifier: Topic :: System :: Archiving :: Compression
Classifier: Topic :: System :: Filesystems
Classifier: Topic :: Internet
Classifier: Environment :: Console
Requires-Python: >=3.11
License-File: LICENSE
Requires-Dist: boto3>=1.35.0
Requires-Dist: click>=8.1.0
Requires-Dist: cryptography>=42.0.0
Requires-Dist: python-dateutil>=2.9.0
Requires-Dist: requests>=2.32.0
Provides-Extra: dev
Requires-Dist: pytest>=8.0.0; extra == "dev"
Requires-Dist: pytest-mock>=3.14.0; extra == "dev"
Requires-Dist: pytest-asyncio>=0.24.0; extra == "dev"
Requires-Dist: moto[s3]>=5.0.0; extra == "dev"
Requires-Dist: ruff>=0.8.0; extra == "dev"
Requires-Dist: mypy>=1.13.0; extra == "dev"
Requires-Dist: boto3-stubs[s3]>=1.35.0; extra == "dev"
Requires-Dist: types-python-dateutil>=2.9.0; extra == "dev"
Dynamic: license-file
